debugpypi/__init__.py
debugpypi/print_str.py
wenjuanpro/__init__.py
wenjuanpro/print_str.py
wenjuantest2/__init__.py
wenjuantest2/print_str.py
wenjuantest22/__init__.py
wenjuantest22/print_str.py
wenjuantest33/__init__.py
wenjuantest33/print_str.py
wenjuantest33-0.0.1.dist-info/METADATA
wenjuantest33-0.0.1.dist-info/WHEEL
wenjuantest33-0.0.1.dist-info/top_level.txt
wenjuantest33-0.0.1.dist-info/RECORD
