Metadata-Version: 2.1
Name: wenjuantest33
Version: 0.0.1
Summary: 美丽的星空
Home-page: https://github.com/
Author: kagome
Maintainer: another
Maintainer-email: fengshaomin@qq.com
License: UNKNOWN
Platform: UNKNOWN
Classifier: Programming Language :: Python :: 3
Classifier: License :: OSI Approved :: MIT License
Classifier: Operating System :: OS Independent
